circuitry/__init__.py
circuitry/circuitry.py
circuitry-2.0.0.dist-info/LICENSE
circuitry-2.0.0.dist-info/METADATA
circuitry-2.0.0.dist-info/WHEEL
circuitry-2.0.0.dist-info/top_level.txt
circuitry-2.0.0.dist-info/RECORD
