Metadata-Version: 2.1
Name: circuitry
Version: 2.0.0
Summary: Embedded domain-specific combinator library for the abstract assembly and automated synthesis of logical circuits.
Author: Andrei Lapets
Author-email: a@lapets.io
License: MIT
Project-URL: Repository, https://github.com/nthparty/circuitry
Project-URL: Documentation, https://circuitry.readthedocs.io
Requires-Python: >=3.7
License-File: LICENSE
Requires-Dist: parts (~=1.5)
Requires-Dist: bitlist (~=1.0)
Requires-Dist: circuit (~=2.0)
Provides-Extra: coveralls
Requires-Dist: coveralls (~=3.3.1) ; extra == 'coveralls'
Provides-Extra: docs
Requires-Dist: toml (~=0.10.2) ; extra == 'docs'
Requires-Dist: sphinx (~=4.2.0) ; extra == 'docs'
Requires-Dist: sphinx-rtd-theme (~=1.0.0) ; extra == 'docs'
Provides-Extra: lint
Requires-Dist: pylint (~=2.14.0) ; extra == 'lint'
Provides-Extra: publish
Requires-Dist: twine (~=4.0) ; extra == 'publish'
Provides-Extra: test
Requires-Dist: pytest (~=7.0) ; extra == 'test'
Requires-Dist: pytest-cov (~=3.0) ; extra == 'test'
